README.md
setup.py
PROMINENT_methylation/dataprep.py
PROMINENT_methylation/interpret.py
PROMINENT_methylation/model.py
PROMINENT_methylation/scores.py
PROMINENT_methylation/train.py
PROMINENT_methylation/train_test.py
PROMINENT_methylation/utils.py
PROMINENT_methylation.egg-info/PKG-INFO
PROMINENT_methylation.egg-info/SOURCES.txt
PROMINENT_methylation.egg-info/dependency_links.txt
PROMINENT_methylation.egg-info/entry_points.txt
PROMINENT_methylation.egg-info/requires.txt
PROMINENT_methylation.egg-info/top_level.txt